tennisrank/__init__.py
tennisrank/algorithm.py
tennisrank/cache.py
tennisrank/model.py
tennisrank/utils.py
tennisrank-0.1.8.dist-info/LICENSE
tennisrank-0.1.8.dist-info/METADATA
tennisrank-0.1.8.dist-info/WHEEL
tennisrank-0.1.8.dist-info/top_level.txt
tennisrank-0.1.8.dist-info/RECORD
