Metadata-Version: 2.1
Name: tennisrank
Version: 0.1.8
Summary: Library for ranking tennis players
Requires-Python: >=3.7
License-File: LICENSE
Requires-Dist: networkx[default] ~=3.2.1
Requires-Dist: requests
Requires-Dist: appdirs ~=1.4.4
Provides-Extra: tests
Requires-Dist: build ; extra == 'tests'
Requires-Dist: twine ; extra == 'tests'
Requires-Dist: pytest ; extra == 'tests'
Requires-Dist: flake8 ; extra == 'tests'
